{
    "success": true,
    "fields": {
      "title": "From Concept to, \u003Cbr/\u003EConnection.",
      "description": "Design is more than just\r\ncreating visuals, it’s\r\nabout crafting experiences, shaping emotions,\r\nand telling stories that leave a\r\nlasting impression.",
      "gallery": [
        "https://dashboard.farzad-k.com/wp-content/uploads/2025/08/3-iPad-Mockup_result-1024x768-1.jpg",
        "https://dashboard.farzad-k.com/wp-content/uploads/2025/08/Desktop-4-1024x1024-1.jpg",
        "https://dashboard.farzad-k.com/wp-content/uploads/2025/08/dorr-f-1-1024x576.jpg",
        "https://dashboard.farzad-k.com/wp-content/uploads/2025/08/theweeknd14.jpg",
        "https://dashboard.farzad-k.com/wp-content/uploads/2025/08/gillamoon-f-1-1024x678.webp",
        "https://dashboard.farzad-k.com/wp-content/uploads/2025/08/negin-motor-14.jpg"
      ],
      "logos": [
        "https://dashboard.farzad-k.com/wp-content/uploads/2025/08/logo-raad-3.png",
        "https://dashboard.farzad-k.com/wp-content/uploads/2025/08/logo-designex-4.svg",
        "https://dashboard.farzad-k.com/wp-content/uploads/2025/08/logo-lotus-2.svg",
        "https://dashboard.farzad-k.com/wp-content/uploads/2025/08/logo-mivinna-5.svg",
        "https://dashboard.farzad-k.com/wp-content/uploads/2025/08/logo-pak-1.svg"
      ],
      "hworks": [
        {
          "title": " Let’s Talk.",
          "text": "\u003Cp\u003EWe start with a quick conversation via email, video call, or in person. We’ll discuss your goals, your brand’s challenges, and the results you’re looking to achieve. No pressure, just a genuine conversation to see if we’re the right fit to work together.\u003C/p\u003E\n",
          "link": {
            "title": "About us",
            "url": "about",
            "target": ""
          }
        },
        {
          "title": "Discovery & Planning.",
          "text": "\u003Cp class=\"text__24 opacity-80\"\u003EOnce we align, I’ll define the creative and strategic direction, from brand positioning and design concepts to project scope and timeline.\u003C/p\u003E\n\u003Cp class=\"text__24 opacity-80 mt-4\"\u003EIncludes:\u003C/p\u003E\n\u003Cul\u003E\n\u003Cli\u003EBrand &amp; market research\u003C/li\u003E\n\u003Cli\u003EUser or audience insights\u003C/li\u003E\n\u003Cli\u003EProject scope, milestones, and deliverables\u003C/li\u003E\n\u003Cli\u003Eustom proposal &amp; agreement\u003C/li\u003E\n\u003C/ul\u003E\n",
          "link": {
            "title": "About us",
            "url": "about",
            "target": ""
          }
        },
        {
          "title": " Design & Development.",
          "text": "\u003Cp class=\"text__24 opacity-80\"\u003EThis is where ideas take shape creating concepts, prototypes, and refined designs for your product, brand, or packaging. Every detail is intentional, balancing creativity with functionality.\u003C/p\u003E\n\u003Cp class=\"text__24 opacity-80 mt-4\"\u003EIncludes:\u003C/p\u003E\n\u003Cul\u003E\n\u003Cli\u003EConcept exploration &amp; design iterations\u003C/li\u003E\n\u003Cli\u003EWireframes, mockups, or prototypes\u003C/li\u003E\n\u003Cli\u003EVisual identity elements and brand assets\u003C/li\u003E\n\u003Cli\u003EFeedback and refinement rounds\u003C/li\u003E\n\u003C/ul\u003E\n",
          "link": {
            "title": "About us",
            "url": "about",
            "target": ""
          }
        },
        {
          "title": " Finalization & Handoff.",
          "text": "\u003Cp class=\"text__24 opacity-80\"\u003EOnce the designs are approved, I prepare all files, guidelines, and assets you’ll need ensuring they’re ready for implementation across digital and print.\u003C/p\u003E\n\u003Cp class=\"text__24 opacity-80 mt-4\"\u003EIncludes:\u003C/p\u003E\n\u003Cul\u003E\n\u003Cli\u003EFinal design files in all necessary formats\u003C/li\u003E\n\u003Cli\u003EBrand or design system guidelines\u003C/li\u003E\n\u003Cli\u003EDeveloper-ready assets or print-ready dielines\u003C/li\u003E\n\u003Cli\u003EOptional production and launch support\u003C/li\u003E\n\u003C/ul\u003E\n",
          "link": {
            "title": "About us",
            "url": "about",
            "target": ""
          }
        },
        {
          "title": " Delivery & Payment.",
          "text": "\u003Cp class=\"text__24 opacity-80\"\u003EYou’ll receive your final deliverables polished, on-brand, and ready to launch. Final payment is due upon delivery.\u003C/p\u003E\n\u003Cp class=\"text__24 opacity-80 mt-4\"\u003EPayment Options:\u003C/p\u003E\n\u003Cul\u003E\n\u003Cli\u003EBank transfer\u003C/li\u003E\n\u003Cli\u003EPayPal / Wise\u003C/li\u003E\n\u003Cli\u003E50% upfront / 50% on delivery (for most projects)\u003C/li\u003E\n\u003C/ul\u003E\n",
          "link": {
            "title": "About us",
            "url": "about",
            "target": ""
          }
        }
      ],
      "aw": [
        {
          "title": "Awwwards",
          "logo": "https://dashboard.farzad-k.com/wp-content/uploads/2025/08/awwards.svg",
          "award": {
            "count": 16,
            "items": [
              {
                "titlee": "Honorable Mention",
                "date": "Sep 20, 2024",
                "link": "https://www.awwwards.com/sites/dorr-architects"
              },
              {
                "titlee": "Honorable Mention",
                "date": "Sep 11, 2024",
                "link": "https://www.awwwards.com/sites/dokmeh-creative-agency-2"
              },
              {
                "titlee": "Nominee",
                "date": "Dec 27, 2023",
                "link": "https://www.awwwards.com/sites/dokmeh-creative-agency"
              },
              {
                "titlee": "Nominee",
                "date": "Dec 11, 2023",
                "link": "https://www.awwwards.com/sites/red-stories-of-experiment"
              },
              {
                "titlee": "Nominee",
                "date": "Sep 28, 2022",
                "link": "https://www.awwwards.com/sites/lobat"
              },
              {
                "titlee": "Nominee",
                "date": "Jul 4, 2023",
                "link": "https://www.awwwards.com/sites/fma-architects"
              },
              {
                "titlee": "Nominee",
                "date": "Oct 17, 2022",
                "link": "https://www.awwwards.com/sites/todoesdata"
              },
              {
                "titlee": "Honorable Mention",
                "date": "Jul 9, 2019",
                "link": "https://www.awwwards.com/sites/z-1"
              },
              {
                "titlee": "Honorable Mention",
                "date": "Sep 3, 2019",
                "link": "https://www.awwwards.com/sites/masoudrostami-official-website"
              },
              {
                "titlee": "Honorable Mention",
                "date": "Sep 28, 2022",
                "link": "https://www.awwwards.com/sites/design-kki"
              },
              {
                "titlee": "Honorable Mention",
                "date": "Sep 15, 2022",
                "link": "https://www.awwwards.com/sites/dokmeh-agency"
              },
              {
                "titlee": "Nominee",
                "date": "Nov 4, 2019",
                "link": "https://www.awwwards.com/sites/amir-hossein-akhavan"
              },
              {
                "titlee": "Nominee",
                "date": "Nov 4, 2019",
                "link": "https://www.awwwards.com/sites/nahal-hamidi-official-website"
              },
              {
                "titlee": "Nominee",
                "date": "Oct 28, 2019",
                "link": "https://www.awwwards.com/sites/cedrus-architects"
              },
              {
                "titlee": "Nominee",
                "date": "Oct 7, 2019",
                "link": "https://www.awwwards.com/sites/behrang-sohrabi"
              },
              {
                "titlee": "Honorable Mention",
                "date": "Oct 7, 2019",
                "link": "https://www.awwwards.com/sites/shift-process-practice"
              }
            ]
          }
        },
        {
          "title": "CSS Design Awards (CSSDA)",
          "logo": "https://dashboard.farzad-k.com/wp-content/uploads/2025/08/c-d-a.svg",
          "award": {
            "count": 13,
            "items": [
              {
                "titlee": "Special Kudos",
                "date": "2024 Nov 09",
                "link": "https://www.cssdesignawards.com/sites/dorr-architecture-group/46560/"
              },
              {
                "titlee": "Special Kudos",
                "date": "2024 Mar 22",
                "link": "https://www.cssdesignawards.com/sites/dokmeh-agency-2024/45330/"
              },
              {
                "titlee": "Special Kudos",
                "date": "2022 Sep 13",
                "link": "https://www.cssdesignawards.com/sites/dokmeh-agency/41984/"
              },
              {
                "titlee": "Special Kudos",
                "date": "2021 Sep 5",
                "link": "https://www.cssdesignawards.com/sites/khesht-o-khorshid/39677/"
              },
              {
                "titlee": "Special Kudos",
                "date": "2021 Mar 6",
                "link": "https://www.cssdesignawards.com/sites/ali-kourehchian/38735/"
              },
              {
                "titlee": "Special Kudos",
                "date": "2020 Apr 3",
                "link": "https://www.cssdesignawards.com/sites/farho-architects/36879/"
              },
              {
                "titlee": "Special Kudos",
                "date": "2019 Jul 23",
                "link": "https://www.cssdesignawards.com/sites/cedrus-architects/35499/"
              },
              {
                "titlee": "Website Of The Day",
                "date": "2019 Jun 14",
                "link": "https://www.cssdesignawards.com/sites/z/35314/"
              },
              {
                "titlee": "Special Kudos",
                "date": "2018 Oct 2",
                "link": "https://www.cssdesignawards.com/sites/masoud-rostami/33762/"
              },
              {
                "titlee": "Special Kudos",
                "date": "2017 Jun 22",
                "link": "https://www.cssdesignawards.com/sites/tdc-office/30873/"
              },
              {
                "titlee": "Special Kudos",
                "date": "2017 Mar 28",
                "link": "https://www.cssdesignawards.com/sites/rena-design/30311/"
              },
              {
                "titlee": "Special Kudos",
                "date": "2017 Mar 10",
                "link": "https://www.cssdesignawards.com/sites/nextoffice/30216/"
              },
              {
                "titlee": "Special Kudos",
                "date": "2017 Feb 20",
                "link": "https://www.cssdesignawards.com/sites/rooydaad-architects/30096/"
              }
            ]
          }
        },
        {
          "title": "CSS Winner",
          "logo": "https://dashboard.farzad-k.com/wp-content/uploads/2025/08/csswinner-logo.svg",
          "award": {
            "count": 13,
            "items": [
              {
                "titlee": "Star",
                "date": "11 Sep 2024",
                "link": "https://www.csswinner.com/details/royal-jeans-landing-page/18250"
              },
              {
                "titlee": "Site of the Day",
                "date": "17 Jul 2024",
                "link": "https://www.csswinner.com/details/dorr-architects/18155"
              },
              {
                "titlee": "Site of the Day",
                "date": "21 Mar 2024",
                "link": "https://www.csswinner.com/details/dokmeh-agency/17902"
              },
              {
                "titlee": "Star",
                "date": "20 Sep 2021",
                "link": "https://www.csswinner.com/details/paadiran/15649"
              },
              {
                "titlee": "Site of the Day",
                "date": "01 Sep 2021",
                "link": "https://www.csswinner.com/details/khesht-o-khorshid/15622"
              },
              {
                "titlee": "Star",
                "date": "06 Apr 2020",
                "link": "https://www.csswinner.com/details/farho-architects/14389"
              },
              {
                "titlee": "Site of the Day",
                "date": "23 Jul 2019",
                "link": "https://www.csswinner.com/details/cedrus-architects/13753"
              },
              {
                "titlee": "Site of the Day",
                "date": "15 Jun 2019",
                "link": "https://www.csswinner.com/details/z/13650"
              },
              {
                "titlee": "Site of the Day",
                "date": "24 Sep 2018",
                "link": "https://www.csswinner.com/details/z/13650"
              },
              {
                "titlee": "Star",
                "date": "16 Jun 2017",
                "link": "https://www.csswinner.com/details/tdc-office/11621"
              },
              {
                "titlee": "Nominee",
                "date": "28 Feb 2017",
                "link": "https://www.csswinner.com/details/rena-design/11353"
              },
              {
                "titlee": "Nominee",
                "date": "18 Mar 2017",
                "link": "https://www.csswinner.com/details/nextoffice/11301"
              },
              {
                "titlee": "Star",
                "date": "22 Feb 2017",
                "link": "https://www.csswinner.com/details/rooydaad-architects/11278"
              }
            ]
          }
        }
      ],
      "desktop_image": "https://dashboard.farzad-k.com/wp-content/uploads/2025/08/Generated-Image-August-31-2025-2_47PM.jpg",
      "mobile_image": "https://dashboard.farzad-k.com/wp-content/uploads/2025/08/Generated-Image-August-31-2025-2_17PM.webp"
    }
  }